MANIFEST.in
README.rst
requirements-dev.txt
requirements.txt
setup.cfg
setup.py
melissa/__init__.py
melissa/__main__.py
melissa/actions_db.py
melissa/brain.py
melissa/message_checker.py
melissa/profile.py
melissa/profile_loader.py
melissa/profile_populator.py
melissa/tts.py
melissa.egg-info/PKG-INFO
melissa.egg-info/SOURCES.txt
melissa.egg-info/dependency_links.txt
melissa.egg-info/entry_points.txt
melissa.egg-info/not-zip-safe
melissa.egg-info/requires.txt
melissa.egg-info/top_level.txt
melissa/actions/__init__.py
melissa/actions/business_news_reader.py
melissa/actions/define_subject.py
melissa/actions/find_iphone.py
melissa/actions/general_conversations.py
melissa/actions/horoscope.py
melissa/actions/imgur_handler.py
melissa/actions/ip_address.py
melissa/actions/lighting.py
melissa/actions/notes.py
melissa/actions/notification.py
melissa/actions/play_music.py
melissa/actions/repeat.py
melissa/actions/self_destruct.py
melissa/actions/sleep.py
melissa/actions/spelling.py
melissa/actions/system_status.py
melissa/actions/tell_joke.py
melissa/actions/tell_time.py
melissa/actions/twitter_interaction.py
melissa/actions/weather.py
melissa/data/memory.db.default
melissa/static/css/NeogreyRegular.otf
melissa/static/css/all.css
melissa/static/images/bgAnim1.png
melissa/static/images/bgAnim2.png
melissa/static/images/bgAnim3.png
melissa/static/images/fauxBG.png
melissa/static/images/fauxBG1.png
melissa/static/images/fauxBG2.png
melissa/static/images/fauxBG3.png
melissa/static/images/fauxBG4.png
melissa/static/images/fauxBG5.png
melissa/static/images/footer.png
melissa/static/images/footerGraph.png
melissa/static/images/imageGalBorder.png
melissa/static/images/lock.png
melissa/static/images/lock1.png
melissa/static/images/popup.png
melissa/static/images/sideLiBG.png
melissa/static/images/sideLiBGHover.png
melissa/static/images/singraph.png
melissa/static/images/unlock.png
melissa/static/images/welcomeRing1G.png
melissa/static/images/welcomeRing1R.png
melissa/static/images/welcomeRing2G.png
melissa/static/images/welcomeRing2R.png
melissa/static/images/welcomeRing3G.png
melissa/static/images/welcomeRing3R.png
melissa/static/js/all.js
melissa/static/js/jquery-2.1.0.min.js
