Metadata-Version: 1.2
Name: melissa
Version: 1000.0.34
Summary: A lovely virtual assistant for OS X, Windows and Linux systems.
Home-page: https://github.com/Melissa-AI/Melissa-Core/
Author: Tanay Pant
Author-email: tanay1337@gmail.com
License: MIT
Keywords: virtual assistant speech-to-text text-to-speech melissa jarvis
Platform: UNKNOWN
Classifier: Intended Audience :: Developers
Classifier: License :: OSI Approved :: MIT License
Classifier: Natural Language :: English
Classifier: Programming Language :: Python :: 2.7
Classifier: Programming Language :: Python
Classifier: Programming Language :: Python
Requires-Python: ==2.7.*
